patchfm/__init__.py
patchfm/configs/model_config.py
patchfm/inference/forecaster.py
patchfm/inference/modules.py
patchfm-2.0.1.dist-info/licenses/LICENSE
patchfm-2.0.1.dist-info/METADATA
patchfm-2.0.1.dist-info/WHEEL
patchfm-2.0.1.dist-info/top_level.txt
patchfm-2.0.1.dist-info/RECORD
