Metadata-Version: 2.4
Name: patchfm
Version: 2.0.1
Summary: a Foundation Model for Univariate Time Series Forecasting
Author-email: Samy-Melwan Vilhes <samy-melwan.vilhes@insa-rouen.fr>
License: MIT License
Project-URL: Repository, https://github.com/vilhess/PatchFM
Project-URL: Issues, https://github.com/vilhess/PatchFM/issues
Keywords: Transformer,LLM,Time Series,Zero-shot,Deep Learning
Classifier: Programming Language :: Python :: 3
Classifier: Operating System :: OS Independent
Requires-Python: >=3.11
License-File: LICENSE
Requires-Dist: torch>=2.5.0
Requires-Dist: einops>=0.8.1
Requires-Dist: huggingface-hub>=0.35.1
Requires-Dist: rotary-embedding-torch>=0.8.9
Requires-Dist: numpy>=1.26.0
Requires-Dist: safetensors==0.5.3
Dynamic: license-file
